[{"lat": -34.587134, "lon": -58.389993, "evento": "Atasco tr\u00e1fico denso", "street": "Av. Alvear", "nearest_intersection": "Intersecci\u00f3n desconocida"}, {"lat": -34.585688, "lon": -58.43012, "evento": "Atasco tr\u00e1fico denso", "street": "Fr. Justo Sta. Mar\u00eda de Oro", "nearest_intersection": "Intersecci\u00f3n desconocida"}, {"lat": -34.606752, "lon": -58.508901, "evento": "Via cerrada", "street": "Gualeguaych\u00fa", "nearest_intersection": "Intersecci\u00f3n desconocida"}, {"lat": -34.599279, "lon": -58.389699, "evento": "Falla de sem\u00e1foro", "street": "Montevideo", "nearest_intersection": "Intersecci\u00f3n desconocida"}, {"lat": -34.648927, "lon": -58.475477, "evento": "Atasco tr\u00e1fico denso", "street": "AU 6 Perito Moreno", "nearest_intersection": "Intersecci\u00f3n desconocida"}, {"lat": -34.589291, "lon": -58.382244, "evento": "Atasco tr\u00e1fico pesado", "street": "Cerrito", "nearest_intersection": "Intersecci\u00f3n desconocida"}, {"lat": -34.64031, "lon": -58.458661, "evento": "Veh\u00edculo detenido", "street": "Autopista 25 de Mayo", "nearest_intersection": "Intersecci\u00f3n desconocida"}, {"lat": -34.657395, "lon": -58.469826, "evento": "Via cerrada", "street": "Calle desconocida", "nearest_intersection": "Intersecci\u00f3n desconocida"}, {"lat": -34.642127, "lon": -58.381011, "evento": "Via cerrada", "street": "Dr. Ram\u00f3n Carrillo", "nearest_intersection": "Intersecci\u00f3n desconocida"}, {"lat": -34.595258, "lon": -58.387217, "evento": "Baches en el camino", "street": "Uruguay", "nearest_intersection": "Intersecci\u00f3n desconocida"}, {"lat": -34.594139, "lon": -58.419643, "evento": "Baches en el camino", "street": "Av. Honduras", "nearest_intersection": "Intersecci\u00f3n desconocida"}, {"lat": -34.663703, "lon": -58.417355, "evento": "Baches en el camino", "street": "Av. Remedios de Escalada de San Mart\u00edn", "nearest_intersection": "Intersecci\u00f3n desconocida"}, {"lat": -34.626263, "lon": -58.471624, "evento": "Obras en la calzada", "street": "Av. Nazca", "nearest_intersection": "Intersecci\u00f3n desconocida"}, {"lat": -34.570769, "lon": -58.421161, "evento": "Via cerrada", "street": "Calle desconocida", "nearest_intersection": "Intersecci\u00f3n desconocida"}, {"lat": -34.603718, "lon": -58.453529, "evento": "Via cerrada", "street": "Dr. Luis Bel\u00e1ustegui", "nearest_intersection": "Intersecci\u00f3n desconocida"}, {"lat": -34.589522, "lon": -58.445137, "evento": "Obras en la calzada", "street": "Juan Ram\u00edrez de Velasco", "nearest_intersection": "Intersecci\u00f3n desconocida"}, {"lat": -34.661029, "lon": -58.471655, "evento": "Veh\u00edculo detenido", "street": "AU Tte. Gral. Luis Dellepiane", "nearest_intersection": "Intersecci\u00f3n desconocida"}, {"lat": -34.589514, "lon": -58.372389, "evento": "Baches en el camino", "street": "Av. Dr. Jos\u00e9 Mar\u00eda Ramos Mej\u00eda", "nearest_intersection": "Intersecci\u00f3n desconocida"}, {"lat": -34.60951, "lon": -58.410407, "evento": "Atasco tr\u00e1fico denso", "street": "Jean Jaures", "nearest_intersection": "Intersecci\u00f3n desconocida"}, {"lat": -34.563139, "lon": -58.455898, "evento": "Atasco tr\u00e1fico denso", "street": "Av. Cabildo", "nearest_intersection": "Intersecci\u00f3n desconocida"}, {"lat": -34.599788, "lon": -58.429731, "evento": "Via cerrada", "street": "Lambar\u00e9", "nearest_intersection": "Intersecci\u00f3n desconocida"}, {"lat": -34.608713, "lon": -58.430418, "evento": "Peligro en calle", "street": "Av. D\u00edaz V\u00e9lez", "nearest_intersection": "Intersecci\u00f3n desconocida"}, {"lat": -34.628452, "lon": -58.423734, "evento": "Atasco tr\u00e1fico denso", "street": "Autopista 25 de Mayo", "nearest_intersection": "Intersecci\u00f3n desconocida"}, {"lat": -34.65943, "lon": -58.470882, "evento": "Via cerrada", "street": "Mozart", "nearest_intersection": "Intersecci\u00f3n desconocida"}, {"lat": -34.585887, "lon": -58.385055, "evento": "Via cerrada", "street": "Brig. Gral. Juan Facundo Quiroga", "nearest_intersection": "Intersecci\u00f3n desconocida"}, {"lat": -34.661202, "lon": -58.388208, "evento": "Baches en el camino", "street": "Puente Victorino de la Plaza", "nearest_intersection": "Intersecci\u00f3n desconocida"}, {"lat": -34.657766, "lon": -58.469682, "evento": "Via cerrada", "street": "Calle desconocida", "nearest_intersection": "Intersecci\u00f3n desconocida"}, {"lat": -34.635951, "lon": -58.495282, "evento": "Via cerrada", "street": "Yerbal", "nearest_intersection": "Intersecci\u00f3n desconocida"}, {"lat": -34.563598, "lon": -58.455507, "evento": "Baches en el camino", "street": "Av. Cabildo", "nearest_intersection": "Intersecci\u00f3n desconocida"}, {"lat": -34.657038, "lon": -58.37833, "evento": "Via cerrada", "street": "Calle desconocida", "nearest_intersection": "Intersecci\u00f3n desconocida"}, {"lat": -34.604676, "lon": -58.458624, "evento": "Atasco tr\u00e1fico pesado", "street": "Av. Juan B. Justo", "nearest_intersection": "Intersecci\u00f3n desconocida"}, {"lat": -34.599788, "lon": -58.429731, "evento": "Via cerrada", "street": "Guardia Vieja", "nearest_intersection": "Intersecci\u00f3n desconocida"}, {"lat": -34.638566, "lon": -58.456167, "evento": "Veh\u00edculo detenido", "street": "Autopista 25 de Mayo", "nearest_intersection": "Intersecci\u00f3n desconocida"}, {"lat": -34.592851, "lon": -58.378596, "evento": "Via cerrada", "street": "Juncal", "nearest_intersection": "Intersecci\u00f3n desconocida"}, {"lat": -34.588412, "lon": -58.414837, "evento": "Obras en la calzada", "street": "Jer\u00f3nimo Salguero", "nearest_intersection": "Intersecci\u00f3n desconocida"}, {"lat": -34.596505, "lon": -58.419963, "evento": "Via cerrada", "street": "Jos\u00e9 Antonio Cabrera", "nearest_intersection": "Intersecci\u00f3n desconocida"}, {"lat": -34.64953, "lon": -58.468393, "evento": "Atasco tr\u00e1fico pesado", "street": "Autopista 25 de Mayo", "nearest_intersection": "Intersecci\u00f3n desconocida"}, {"lat": -34.615268, "lon": -58.425948, "evento": "Baches en el camino", "street": "Jos\u00e9 M\u00e1rmol", "nearest_intersection": "Intersecci\u00f3n desconocida"}, {"lat": -34.606437, "lon": -58.440175, "evento": "Obras en la calzada", "street": "Acoyte", "nearest_intersection": "Intersecci\u00f3n desconocida"}, {"lat": -34.570974, "lon": -58.421256, "evento": "Via cerrada", "street": "Calle desconocida", "nearest_intersection": "Intersecci\u00f3n desconocida"}, {"lat": -34.542584, "lon": -58.449356, "evento": "Obras en la calzada", "street": "Av. Leopoldo Lugones", "nearest_intersection": "Intersecci\u00f3n desconocida"}, {"lat": -34.625897, "lon": -58.403051, "evento": "Via cerrada", "street": "Calle desconocida", "nearest_intersection": "Intersecci\u00f3n desconocida"}, {"lat": -34.606714, "lon": -58.447278, "evento": "Baches en el camino", "street": "Antezana", "nearest_intersection": "Intersecci\u00f3n desconocida"}, {"lat": -34.578632, "lon": -58.470834, "evento": "Obras en la calzada", "street": "Donado", "nearest_intersection": "Intersecci\u00f3n desconocida"}, {"lat": -34.599945, "lon": -58.428169, "evento": "Via cerrada", "street": "Guardia Vieja", "nearest_intersection": "Intersecci\u00f3n desconocida"}, {"lat": -34.627469, "lon": -58.41657, "evento": "", "street": "Autopista 25 de Mayo", "nearest_intersection": "Intersecci\u00f3n desconocida"}, {"lat": -34.657144, "lon": -58.381218, "evento": "Via cerrada", "street": "Calle desconocida", "nearest_intersection": "Intersecci\u00f3n desconocida"}, {"lat": -34.577119, "lon": -58.458087, "evento": "Baches en el camino", "street": "Delgado", "nearest_intersection": "Intersecci\u00f3n desconocida"}, {"lat": -34.569813, "lon": -58.457928, "evento": "Via cerrada", "street": "Av. de los Incas", "nearest_intersection": "Intersecci\u00f3n desconocida"}, {"lat": -34.579771, "lon": -58.475349, "evento": "", "street": "Giribone", "nearest_intersection": "Intersecci\u00f3n desconocida"}, {"lat": -34.606099, "lon": -58.367778, "evento": "Atasco tr\u00e1fico pesado", "street": "Av. Eduardo Madero", "nearest_intersection": "Intersecci\u00f3n desconocida"}, {"lat": -34.682203, "lon": -58.481301, "evento": "Veh\u00edculo detenido", "street": "AU Tte. Gral. Luis Dellepiane", "nearest_intersection": "Intersecci\u00f3n desconocida"}, {"lat": -34.654354, "lon": -58.499073, "evento": "Baches en el camino", "street": "Jos\u00e9 Enrique Rod\u00f3", "nearest_intersection": "Intersecci\u00f3n desconocida"}, {"lat": -34.609838, "lon": -58.401598, "evento": "Atasco tr\u00e1fico denso", "street": "Av. Rivadavia", "nearest_intersection": "Intersecci\u00f3n desconocida"}, {"lat": -34.635674, "lon": -58.493828, "evento": "Via cerrada", "street": "Yerbal", "nearest_intersection": "Intersecci\u00f3n desconocida"}, {"lat": -34.636059, "lon": -58.496159, "evento": "Via cerrada", "street": "Yerbal", "nearest_intersection": "Intersecci\u00f3n desconocida"}, {"lat": -34.603609, "lon": -58.37003, "evento": "", "street": "Av. Leandro N. Alem", "nearest_intersection": "Intersecci\u00f3n desconocida"}, {"lat": -34.599216, "lon": -58.429592, "evento": "Via cerrada", "street": "Lambar\u00e9", "nearest_intersection": "Intersecci\u00f3n desconocida"}, {"lat": -34.609987, "lon": -58.366471, "evento": "Veh\u00edculo detenido", "street": "Av. Alicia Moreau de Justo", "nearest_intersection": "Intersecci\u00f3n desconocida"}, {"lat": -34.597466, "lon": -58.393169, "evento": "Falla de sem\u00e1foro", "street": "Av. Callao", "nearest_intersection": "Intersecci\u00f3n desconocida"}, {"lat": -34.618661, "lon": -58.418206, "evento": "", "street": "Agrelo", "nearest_intersection": "Intersecci\u00f3n desconocida"}, {"lat": -34.641168, "lon": -58.45985, "evento": "Peligro en calle", "street": "Autopista 25 de Mayo", "nearest_intersection": "Intersecci\u00f3n desconocida"}, {"lat": -34.557516, "lon": -58.458619, "evento": "Atasco tr\u00e1fico denso", "street": "Monroe", "nearest_intersection": "Intersecci\u00f3n desconocida"}, {"lat": -34.59957, "lon": -58.391752, "evento": "Falla de sem\u00e1foro", "street": "Av. C\u00f3rdoba", "nearest_intersection": "Intersecci\u00f3n desconocida"}, {"lat": -34.61018, "lon": -58.36645, "evento": "Veh\u00edculo detenido", "street": "Av. Alicia Moreau de Justo", "nearest_intersection": "Intersecci\u00f3n desconocida"}, {"lat": -34.570361, "lon": -58.457988, "evento": "Via cerrada", "street": "Calle desconocida", "nearest_intersection": "Intersecci\u00f3n desconocida"}, {"lat": -34.553352, "lon": -58.43505, "evento": "Atasco tr\u00e1fico pesado", "street": "Av. Pdte. Figueroa Alcorta", "nearest_intersection": "Intersecci\u00f3n desconocida"}, {"lat": -34.598711, "lon": -58.393339, "evento": "Baches en el camino", "street": "Paraguay", "nearest_intersection": "Intersecci\u00f3n desconocida"}, {"lat": -34.548745, "lon": -58.437314, "evento": "Atasco tr\u00e1fico denso", "street": "Calle desconocida", "nearest_intersection": "Intersecci\u00f3n desconocida"}, {"lat": -34.64363, "lon": -58.486308, "evento": "Obras en la calzada", "street": "Dr. Florentino Ameghino", "nearest_intersection": "Intersecci\u00f3n desconocida"}, {"lat": -34.642019, "lon": -58.470192, "evento": "Obras en la calzada", "street": "Pergamino", "nearest_intersection": "Intersecci\u00f3n desconocida"}, {"lat": -34.567117, "lon": -58.485907, "evento": "Baches en el camino", "street": "Valdenegro", "nearest_intersection": "Intersecci\u00f3n desconocida"}, {"lat": -34.577068, "lon": -58.430199, "evento": "Falla de sem\u00e1foro", "street": "Av. Santa Fe", "nearest_intersection": "Intersecci\u00f3n desconocida"}, {"lat": -34.569471, "lon": -58.478099, "evento": "", "street": "Donado", "nearest_intersection": "Intersecci\u00f3n desconocida"}, {"lat": -34.575787, "lon": -58.425645, "evento": "Atasco tr\u00e1fico denso", "street": "Av. Int. Bullrich", "nearest_intersection": "Intersecci\u00f3n desconocida"}, {"lat": -34.604528, "lon": -58.368039, "evento": "Obras en la calzada", "street": "Av. Eduardo Madero", "nearest_intersection": "Intersecci\u00f3n desconocida"}, {"lat": -34.658799, "lon": -58.470389, "evento": "Via cerrada", "street": "Mozart", "nearest_intersection": "Intersecci\u00f3n desconocida"}, {"lat": -34.626844, "lon": -58.489334, "evento": "Baches en el camino", "street": "Sanabria", "nearest_intersection": "Intersecci\u00f3n desconocida"}, {"lat": -34.62641, "lon": -58.437624, "evento": "Veh\u00edculo detenido", "street": "San Jos\u00e9 de Calasanz", "nearest_intersection": "Intersecci\u00f3n desconocida"}, {"lat": -34.550767, "lon": -58.436992, "evento": "Atasco tr\u00e1fico pesado", "street": "Av. Gral. Paz y Ciudad Universitaria por puente Illia", "nearest_intersection": "Intersecci\u00f3n desconocida"}, {"lat": -34.556397, "lon": -58.481693, "evento": "Veh\u00edculo detenido", "street": "Cris\u00f3logo Larralde", "nearest_intersection": "Intersecci\u00f3n desconocida"}]